MANIFEST.in
setup.py
centrifuge/__init__.py
centrifuge/auth.py
centrifuge/client.py
centrifuge/core.py
centrifuge/handlers.py
centrifuge/log.py
centrifuge/metrics.py
centrifuge/node.py
centrifuge/response.py
centrifuge/schema.py
centrifuge/structure.py
centrifuge/utils.py
centrifuge.egg-info/PKG-INFO
centrifuge.egg-info/SOURCES.txt
centrifuge.egg-info/dependency_links.txt
centrifuge.egg-info/entry_points.txt
centrifuge.egg-info/requires.txt
centrifuge.egg-info/top_level.txt
centrifuge/engine/__init__.py
centrifuge/engine/memory.py
centrifuge/engine/redis.py
centrifuge/web/__init__.py
centrifuge/web/handlers.py
test/test_auth.py
test/test_client.py
test/test_core.py
test/test_engine.py
test/test_metrics.py
test/test_response.py
test/test_schema.py
test/test_structure.py