Metadata-Version: 1.1
Name: centrifuge
Version: 0.8.3
Summary: Simple real-time messaging in web applications
Home-page: http://centrifugal.github.io
Author: Alexandr Emelin
Author-email: frvzmb@gmail.com
License: MIT
Download-URL: https://github.com/centrifugal/centrifuge
Platform: UNKNOWN
Classifier: Development Status :: 4 - Beta
Classifier: Programming Language :: Python
Classifier: Programming Language :: Python :: 2
Classifier: Programming Language :: Python :: 2.6
Classifier: Programming Language :: Python :: 2.7
Classifier: Programming Language :: Python :: 3
Classifier: Programming Language :: Python :: 3.3
Classifier: Programming Language :: Python :: 3.4
Classifier: Environment :: Web Environment
Classifier: Intended Audience :: Developers
Classifier: Intended Audience :: System Administrators
Classifier: License :: OSI Approved :: MIT License
Classifier: Topic :: Internet :: WWW/HTTP
Classifier: Topic :: Software Development
Classifier: Topic :: System :: Networking
Classifier: Topic :: Text Processing
Classifier: Topic :: Utilities
